MANIFEST.in
README.txt
setup.py
ConnyUtils/Common.py
ConnyUtils/Evaluate.py
ConnyUtils/IOUtil.py
ConnyUtils/__init__.py
ConnyUtils/hellomodule.py
ConnyUtils/somePython.py
ConnyUtils.egg-info/PKG-INFO
ConnyUtils.egg-info/SOURCES.txt
ConnyUtils.egg-info/dependency_links.txt
ConnyUtils.egg-info/requires.txt
ConnyUtils.egg-info/top_level.txt
ConnyUtils/packageData/sampleData.dat
ConnyUtils/packageData/skill_relations.txt
ConnyUtils/packageData/skill_synonyms.txt