Metadata-Version: 1.0
Name: ConnyUtils
Version: 0.3
Summary: Some usefull functions for machine learning
Home-page: UNKNOWN
Author: CPflaume
Author-email: constantin.pflaume@gmail.com
License: MIT
Platform: UNKNOWN
